src/__init__.py
src/diceware-passphrase-generator/__init__.py
src/diceware-passphrase-generator/dice.py
src/diceware-passphrase-generator/diceware.py
src/diceware-passphrase-generator/passgen.py
src/diceware-passphrase-generator/wordlist_loader.py
diceware_passphrase_generator-1.0.2.dist-info/METADATA
diceware_passphrase_generator-1.0.2.dist-info/WHEEL
diceware_passphrase_generator-1.0.2.dist-info/licenses/LICENSE
diceware_passphrase_generator-1.0.2.dist-info/RECORD
