Metadata-Version: 2.1
Name: diceware-passphrase-generator
Version: 1.0.2
Summary: This is a command-line tool for generating secure passphrases based on the diceware method.
Project-URL: Homepage, https://github.com/SoSaymon/diceware-passphrase-generator
Project-URL: Bug Tracker, https://github.com/SoSaymon/diceware-passphrase-generator/issues
Author-email: Szymon Chirowski <szymon.chirowski@protonmail.com>
License-File: LICENSE
Classifier: License :: OSI Approved :: MIT License
Classifier: Operating System :: OS Independent
Classifier: Programming Language :: Python :: 3
Requires-Python: >=3.10
